{
    "file-setup-lesson.md": {
        "layout": "post",
        "title": "File Setup Basics",
        "published": "Mar 09, 2021",
        "author": "yonatan119",
        "tags": "css, html",
        "timestamp": 1634563834,
        "location": "file-setup-lesson.md.json"
    },
    "css-html.md": {
        "layout": "post",
        "title": "css-html",
        "published": "Oct 18, 2021",
        "author": "yonatan119",
        "tags": "css, html",
        "timestamp": 1634563834,
        "location": "css-html.md.json"
    }
}